layer_cake/__init__.py
layer_cake/bind_type.py
layer_cake/command_line.py
layer_cake/command_startup.py
layer_cake/convert_memory.py
layer_cake/convert_signature.py
layer_cake/convert_type.py
layer_cake/countdown_timer.py
layer_cake/disk_storage.py
layer_cake/edit_role.py
layer_cake/file_object.py
layer_cake/folder_object.py
layer_cake/general_purpose.py
layer_cake/get_local_ip.py
layer_cake/get_response.py
layer_cake/head_lock.py
layer_cake/home_role.py
layer_cake/http.py
layer_cake/ip_networking.py
layer_cake/json_codec.py
layer_cake/listen_connect.py
layer_cake/log_agent.py
layer_cake/make_message.py
layer_cake/message_memory.py
layer_cake/message_pump.py
layer_cake/noop_codec.py
layer_cake/object_collector.py
layer_cake/object_directory.py
layer_cake/object_logs.py
layer_cake/object_runtime.py
layer_cake/object_space.py
layer_cake/object_spool.py
layer_cake/object_startup.py
layer_cake/parsetab.py
layer_cake/platform_system.py
layer_cake/point_machine.py
layer_cake/point_runtime.py
layer_cake/process_directory.py
layer_cake/process_object.py
layer_cake/retry_intervals.py
layer_cake/rolling_log.py
layer_cake/routine_point.py
layer_cake/running_routine.py
layer_cake/virtual_codec.py
layer_cake/virtual_memory.py
layer_cake/virtual_point.py
layer_cake/virtual_runtime.py
layer_cake/xml_codec.py
script/group_cake.py
script/host_cake.py
script/lan_cake.py
script/layer_cake.py
seven_layer_cake-1.0.10.dist-info/licenses/LICENSE
seven_layer_cake-1.0.10.dist-info/METADATA
seven_layer_cake-1.0.10.dist-info/WHEEL
seven_layer_cake-1.0.10.dist-info/entry_points.txt
seven_layer_cake-1.0.10.dist-info/top_level.txt
seven_layer_cake-1.0.10.dist-info/RECORD
