Metadata-Version: 2.4
Name: seven-layer-cake
Version: 1.0.10
Summary: Concurrency via multithreading, multiprocessing and multihosting
Author-email: "S. Woods" <layer.cake.baker@gmail.com>
License: MIT License
Project-URL: Discussion, https://www.reddit.com/r/layer_cake/
Project-URL: Documentation, https://layer-cake-manual.s3.ap-southeast-2.amazonaws.com/0.1.1/index.html
Keywords: concurrency,multithreading,multiprocessing,asynchronous,networking
Classifier: Development Status :: 4 - Beta
Classifier: Environment :: Console
Classifier: Intended Audience :: Developers
Classifier: Natural Language :: English
Classifier: Operating System :: MacOS
Classifier: Operating System :: Microsoft :: Windows
Classifier: Operating System :: POSIX :: Linux
Classifier: Programming Language :: Python
Classifier: Programming Language :: Python :: 3.9
Classifier: Programming Language :: Python :: 3.10
Classifier: Programming Language :: Python :: 3.11
Classifier: Programming Language :: Python :: 3.12
Classifier: Topic :: Software Development
Classifier: Topic :: Software Development :: Libraries
Classifier: Topic :: Software Development :: Libraries :: Application Frameworks
Classifier: Topic :: Utilities
Requires-Python: >=3.9
License-File: LICENSE
Requires-Dist: cffi
Requires-Dist: PyNaCl
Requires-Dist: ply
Dynamic: license-file
